tf_al/__init__.py
tf_al/acquisition_function.py
tf_al/active_learning_loop.py
tf_al/config.py
tf_al/dataset.py
tf_al/experiment.py
tf_al/experiment_metrics.py
tf_al/experiment_suit.py
tf_al/metrics.py
tf_al/metrics_accumulator.py
tf_al/oracle.py
tf_al/pool.py
tf_al/score/__checks.py
tf_al/score/__init__.py
tf_al/score/label.py
tf_al/score/pool.py
tf_al/score/query.py
tf_al/standard_dataset.py
tf_al/stats/__init__.py
tf_al/stats/metric_dispatcher.py
tf_al/stats/sampling/__init__.py
tf_al/stats/sampling/accuracy.py
tf_al/stats/sampling/auc.py
tf_al/stats/sampling/confusion.py
tf_al/stats/sampling/false_negative.py
tf_al/stats/sampling/false_positive.py
tf_al/stats/sampling/loss.py
tf_al/stats/sampling/true_negative.py
tf_al/stats/sampling/true_positive.py
tf_al/stats/stochastic/__init__.py
tf_al/stats/stochastic/accuracy.py
tf_al/stats/stochastic/auc.py
tf_al/stats/stochastic/loss.py
tf_al/utils/__init__.py
tf_al/utils/acquisition.py
tf_al/utils/logger.py
tf_al/utils/pools.py
tf_al/utils/problem.py
tf_al/utils/tf.py
tf_al/wrapper/__init__.py
tf_al/wrapper/checkpoint.py
tf_al/wrapper/mc_dropout.py
tf_al/wrapper/model.py
tf_al/wrapper/swag.py
tf_al/wrapper/utils.py
tf_al-0.1.1.dist-info/LICENSE
tf_al-0.1.1.dist-info/WHEEL
tf_al-0.1.1.dist-info/METADATA
tf_al-0.1.1.dist-info/RECORD
