Metadata-Version: 2.1
Name: tf-al
Version: 0.1.1
Summary: Active learning with tensorflow. Create custom and generic active learning loops. Export and share your experiments.
Home-page: https://github.com/ExLeonem/tf-al
License: MIT
Keywords: active learning,deep learning,tensorflow
Author: Maksim Sandybekov
Author-email: maksim.sandybekov@live.de
Requires-Python: >=3.6,<4.0
Classifier: License :: OSI Approved :: MIT License
Classifier: Programming Language :: Python :: 3
Classifier: Programming Language :: Python :: 3.6
Classifier: Programming Language :: Python :: 3.7
Classifier: Programming Language :: Python :: 3.8
Classifier: Programming Language :: Python :: 3.9
Requires-Dist: numpy (>=1,<2)
Requires-Dist: scikit-learn (>=0.24.2,<0.25.0)
Requires-Dist: tensorflow (>=2,<3)
Requires-Dist: tqdm (>=4.62.2,<5.0.0)
Project-URL: Repository, https://github.com/ExLeonem/tf-al
